ksu/KSU.py
ksu/Metrics.py
ksu/RunENet.py
ksu/RunKSU.py
ksu/Utils.py
ksu/__init__.py
ksu/__version__.py
ksu/epsilon_net/EpsilonNet.py
ksu/epsilon_net/__init__.py
ksu/tests/TestEpsilonNet.py
ksu/tests/TestMetrics.py
ksu/tests/TestUtils.py
ksu/tests/__init__.py
ksu/tests/main.py
ksu-0.5.1.dist-info/LICENSE
ksu-0.5.1.dist-info/METADATA
ksu-0.5.1.dist-info/WHEEL
ksu-0.5.1.dist-info/entry_points.txt
ksu-0.5.1.dist-info/top_level.txt
ksu-0.5.1.dist-info/RECORD
