Metadata-Version: 2.1
Name: ksu
Version: 0.5.1
Summary: Implementation of the KSU compression algorithm https://www.cs.bgu.ac.il/~karyeh/compression-arxiv.pdf
Home-page: https://github.com/nimroha/ksu_classifier
Author: Nimrod Morag, Yuval Nissan
Author-email: nimrod.morag@gmail.com
License: MIT
Platform: UNKNOWN
Classifier: License :: OSI Approved :: MIT License
Classifier: Programming Language :: Python
Classifier: Programming Language :: Python :: 2
Classifier: Programming Language :: Python :: 2.7
Classifier: Programming Language :: Python :: 3
Classifier: Programming Language :: Python :: 3.5
Classifier: Development Status :: 5 - Production/Stable
Classifier: Intended Audience :: Science/Research
Requires-Python: >=2.7.0
Requires-Dist: numpy
Requires-Dist: sklearn
Requires-Dist: scipy
Requires-Dist: psutil
Requires-Dist: editdistance
Requires-Dist: mnist
Requires-Dist: tqdm
Requires-Dist: requests-toolbelt
Requires-Dist: numba
